{
  "title": "Inside Mari",
  "author": "Shuzo Oshimi",
  "publisher": "Futabasha",
  "cover": "D:\\Project\\crunchymanga\\output\\Inside Mari\\cover.jpg",
  "content": [
    {
      "title": "Chapter 1",
      "data": "<img src=\"D:\\Project\\crunchymanga\\output\\Inside Mari\\ch001_p001.jpg\" title=\"Inside Mari Chapter 1 Page 0\" style=\"page-break-after: always;\"/><img src=\"D:\\Project\\crunchymanga\\output\\Inside Mari\\ch001_p002.jpg\" title=\"Inside Mari Chapter 1 Page 1\" style=\"page-break-after: always;\"/><img src=\"D:\\Project\\crunchymanga\\output\\Inside Mari\\ch001_p003.jpg\" title=\"Inside Mari Chapter 1 Page 2\" style=\"page-break-after: always;\"/><img src=\"D:\\Project\\crunchymanga\\output\\Inside Mari\\ch001_p004.jpg\" title=\"Inside Mari Chapter 1 Page 3\" style=\"page-break-after: always;\"/><img src=\"D:\\Project\\crunchymanga\\output\\Inside Mari\\ch001_p005.jpg\" title=\"Inside Mari Chapter 1 Page 4\" style=\"page-break-after: always;\"/><img src=\"D:\\Project\\crunchymanga\\output\\Inside Mari\\ch001_p006.jpg\" title=\"Inside Mari Chapter 1 Page 5\" style=\"page-break-after: always;\"/><img src=\"D:\\Project\\crunchymanga\\output\\Inside Mari\\ch001_p007.jpg\" title=\"Inside Mari Chapter 1 Page 6\" style=\"page-break-after: always;\"/><img src=\"D:\\Project\\crunchymanga\\output\\Inside Mari\\ch001_p008.jpg\" title=\"Inside Mari Chapter 1 Page 7\" style=\"page-break-after: always;\"/><img src=\"D:\\Project\\crunchymanga\\output\\Inside Mari\\ch001_p009.jpg\" title=\"Inside Mari Chapter 1 Page 8\" style=\"page-break-after: always;\"/><img src=\"D:\\Project\\crunchymanga\\output\\Inside Mari\\ch001_p010.jpg\" title=\"Inside Mari Chapter 1 Page 9\" style=\"page-break-after: always;\"/><img src=\"D:\\Project\\crunchymanga\\output\\Inside Mari\\ch001_p011.jpg\" title=\"Inside Mari Chapter 1 Page 10\" style=\"page-break-after: always;\"/><img src=\"D:\\Project\\crunchymanga\\output\\Inside Mari\\ch001_p012.jpg\" title=\"Inside Mari Chapter 1 Page 11\" style=\"page-break-after: always;\"/><img src=\"D:\\Project\\crunchymanga\\output\\Inside Mari\\ch001_p013.jpg\" title=\"Inside Mari Chapter 1 Page 12\" style=\"page-break-after: always;\"/><img src=\"D:\\Project\\crunchymanga\\output\\Inside Mari\\ch001_p014.jpg\" title=\"Inside Mari Chapter 1 Page 13\" style=\"page-break-after: always;\"/><img src=\"D:\\Project\\crunchymanga\\output\\Inside Mari\\ch001_p015.jpg\" title=\"Inside Mari Chapter 1 Page 14\" style=\"page-break-after: always;\"/><img src=\"D:\\Project\\crunchymanga\\output\\Inside Mari\\ch001_p016.jpg\" title=\"Inside Mari Chapter 1 Page 15\" style=\"page-break-after: always;\"/><img src=\"D:\\Project\\crunchymanga\\output\\Inside Mari\\ch001_p017.jpg\" title=\"Inside Mari Chapter 1 Page 16\" style=\"page-break-after: always;\"/><img src=\"D:\\Project\\crunchymanga\\output\\Inside Mari\\ch001_p018.jpg\" title=\"Inside Mari Chapter 1 Page 17\" style=\"page-break-after: always;\"/><img src=\"D:\\Project\\crunchymanga\\output\\Inside Mari\\ch001_p019.jpg\" title=\"Inside Mari Chapter 1 Page 18\" style=\"page-break-after: always;\"/><img src=\"D:\\Project\\crunchymanga\\output\\Inside Mari\\ch001_p020.jpg\" title=\"Inside Mari Chapter 1 Page 19\" style=\"page-break-after: always;\"/><img src=\"D:\\Project\\crunchymanga\\output\\Inside Mari\\ch001_p021.jpg\" title=\"Inside Mari Chapter 1 Page 20\" style=\"page-break-after: always;\"/><img src=\"D:\\Project\\crunchymanga\\output\\Inside Mari\\ch001_p022.jpg\" title=\"Inside Mari Chapter 1 Page 21\" style=\"page-break-after: always;\"/><img src=\"D:\\Project\\crunchymanga\\output\\Inside Mari\\ch001_p023.jpg\" title=\"Inside Mari Chapter 1 Page 22\" style=\"page-break-after: always;\"/><img src=\"D:\\Project\\crunchymanga\\output\\Inside Mari\\ch001_p024.jpg\" title=\"Inside Mari Chapter 1 Page 23\" style=\"page-break-after: always;\"/><img src=\"D:\\Project\\crunchymanga\\output\\Inside Mari\\ch001_p025.jpg\" title=\"Inside Mari Chapter 1 Page 24\" style=\"page-break-after: always;\"/><img src=\"D:\\Project\\crunchymanga\\output\\Inside Mari\\ch001_p026.jpg\" title=\"Inside Mari Chapter 1 Page 25\" style=\"page-break-after: always;\"/><img src=\"D:\\Project\\crunchymanga\\output\\Inside Mari\\ch001_p027.jpg\" title=\"Inside Mari Chapter 1 Page 26\" style=\"page-break-after: always;\"/><img src=\"D:\\Project\\crunchymanga\\output\\Inside Mari\\ch001_p028.jpg\" title=\"Inside Mari Chapter 1 Page 27\" style=\"page-break-after: always;\"/><img src=\"D:\\Project\\crunchymanga\\output\\Inside Mari\\ch001_p029.jpg\" title=\"Inside Mari Chapter 1 Page 28\" style=\"page-break-after: always;\"/><img src=\"D:\\Project\\crunchymanga\\output\\Inside Mari\\ch001_p030.jpg\" title=\"Inside Mari Chapter 1 Page 29\" style=\"page-break-after: always;\"/><img src=\"D:\\Project\\crunchymanga\\output\\Inside Mari\\ch001_p031.jpg\" title=\"Inside Mari Chapter 1 Page 30\" style=\"page-break-after: always;\"/><img src=\"D:\\Project\\crunchymanga\\output\\Inside Mari\\ch001_p032.jpg\" title=\"Inside Mari Chapter 1 Page 31\" style=\"page-break-after: always;\"/><img src=\"D:\\Project\\crunchymanga\\output\\Inside Mari\\ch001_p033.jpg\" title=\"Inside Mari Chapter 1 Page 32\" style=\"page-break-after: always;\"/><img src=\"D:\\Project\\crunchymanga\\output\\Inside Mari\\ch001_p034.jpg\" title=\"Inside Mari Chapter 1 Page 33\" style=\"page-break-after: always;\"/><img src=\"D:\\Project\\crunchymanga\\output\\Inside Mari\\ch001_p035.jpg\" title=\"Inside Mari Chapter 1 Page 34\" style=\"page-break-after: always;\"/><img src=\"D:\\Project\\crunchymanga\\output\\Inside Mari\\ch001_p036.jpg\" title=\"Inside Mari Chapter 1 Page 35\" style=\"page-break-after: always;\"/><img src=\"D:\\Project\\crunchymanga\\output\\Inside Mari\\ch001_p037.jpg\" title=\"Inside Mari Chapter 1 Page 36\" style=\"page-break-after: always;\"/><img src=\"D:\\Project\\crunchymanga\\output\\Inside Mari\\ch001_p038.jpg\" title=\"Inside Mari Chapter 1 Page 37\" style=\"page-break-after: always;\"/><img src=\"D:\\Project\\crunchymanga\\output\\Inside Mari\\ch001_p039.jpg\" title=\"Inside Mari Chapter 1 Page 38\" style=\"page-break-after: always;\"/><img src=\"D:\\Project\\crunchymanga\\output\\Inside Mari\\ch001_p040.jpg\" title=\"Inside Mari Chapter 1 Page 39\" style=\"page-break-after: always;\"/><img src=\"D:\\Project\\crunchymanga\\output\\Inside Mari\\ch001_p041.jpg\" title=\"Inside Mari Chapter 1 Page 40\" style=\"page-break-after: always;\"/><img src=\"D:\\Project\\crunchymanga\\output\\Inside Mari\\ch001_p042.jpg\" title=\"Inside Mari Chapter 1 Page 41\" style=\"page-break-after: always;\"/>"
    },
    {
      "title": "Chapter 2",
      "data": "<img src=\"D:\\Project\\crunchymanga\\output\\Inside Mari\\ch002_p001.jpg\" title=\"Inside Mari Chapter 2 Page 42\" style=\"page-break-after: always;\"/><img src=\"D:\\Project\\crunchymanga\\output\\Inside Mari\\ch002_p002.jpg\" title=\"Inside Mari Chapter 2 Page 43\" style=\"page-break-after: always;\"/><img src=\"D:\\Project\\crunchymanga\\output\\Inside Mari\\ch002_p003.jpg\" title=\"Inside Mari Chapter 2 Page 44\" style=\"page-break-after: always;\"/><img src=\"D:\\Project\\crunchymanga\\output\\Inside Mari\\ch002_p004.jpg\" title=\"Inside Mari Chapter 2 Page 45\" style=\"page-break-after: always;\"/><img src=\"D:\\Project\\crunchymanga\\output\\Inside Mari\\ch002_p005.jpg\" title=\"Inside Mari Chapter 2 Page 46\" style=\"page-break-after: always;\"/><img src=\"D:\\Project\\crunchymanga\\output\\Inside Mari\\ch002_p006.jpg\" title=\"Inside Mari Chapter 2 Page 47\" style=\"page-break-after: always;\"/><img src=\"D:\\Project\\crunchymanga\\output\\Inside Mari\\ch002_p007.jpg\" title=\"Inside Mari Chapter 2 Page 48\" style=\"page-break-after: always;\"/><img src=\"D:\\Project\\crunchymanga\\output\\Inside Mari\\ch002_p008.jpg\" title=\"Inside Mari Chapter 2 Page 49\" style=\"page-break-after: always;\"/><img src=\"D:\\Project\\crunchymanga\\output\\Inside Mari\\ch002_p009.jpg\" title=\"Inside Mari Chapter 2 Page 50\" style=\"page-break-after: always;\"/><img src=\"D:\\Project\\crunchymanga\\output\\Inside Mari\\ch002_p010.jpg\" title=\"Inside Mari Chapter 2 Page 51\" style=\"page-break-after: always;\"/><img src=\"D:\\Project\\crunchymanga\\output\\Inside Mari\\ch002_p011.jpg\" title=\"Inside Mari Chapter 2 Page 52\" style=\"page-break-after: always;\"/><img src=\"D:\\Project\\crunchymanga\\output\\Inside Mari\\ch002_p012.jpg\" title=\"Inside Mari Chapter 2 Page 53\" style=\"page-break-after: always;\"/><img src=\"D:\\Project\\crunchymanga\\output\\Inside Mari\\ch002_p013.jpg\" title=\"Inside Mari Chapter 2 Page 54\" style=\"page-break-after: always;\"/><img src=\"D:\\Project\\crunchymanga\\output\\Inside Mari\\ch002_p014.jpg\" title=\"Inside Mari Chapter 2 Page 55\" style=\"page-break-after: always;\"/><img src=\"D:\\Project\\crunchymanga\\output\\Inside Mari\\ch002_p015.jpg\" title=\"Inside Mari Chapter 2 Page 56\" style=\"page-break-after: always;\"/><img src=\"D:\\Project\\crunchymanga\\output\\Inside Mari\\ch002_p016.jpg\" title=\"Inside Mari Chapter 2 Page 57\" style=\"page-break-after: always;\"/><img src=\"D:\\Project\\crunchymanga\\output\\Inside Mari\\ch002_p017.jpg\" title=\"Inside Mari Chapter 2 Page 58\" style=\"page-break-after: always;\"/><img src=\"D:\\Project\\crunchymanga\\output\\Inside Mari\\ch002_p018.jpg\" title=\"Inside Mari Chapter 2 Page 59\" style=\"page-break-after: always;\"/><img src=\"D:\\Project\\crunchymanga\\output\\Inside Mari\\ch002_p019.jpg\" title=\"Inside Mari Chapter 2 Page 60\" style=\"page-break-after: always;\"/><img src=\"D:\\Project\\crunchymanga\\output\\Inside Mari\\ch002_p020.jpg\" title=\"Inside Mari Chapter 2 Page 61\" style=\"page-break-after: always;\"/>"
    },
    {
      "title": "Chapter 3",
      "data": "<img src=\"D:\\Project\\crunchymanga\\output\\Inside Mari\\ch003_p001.jpg\" title=\"Inside Mari Chapter 3 Page 62\" style=\"page-break-after: always;\"/><img src=\"D:\\Project\\crunchymanga\\output\\Inside Mari\\ch003_p002.jpg\" title=\"Inside Mari Chapter 3 Page 63\" style=\"page-break-after: always;\"/><img src=\"D:\\Project\\crunchymanga\\output\\Inside Mari\\ch003_p003.jpg\" title=\"Inside Mari Chapter 3 Page 64\" style=\"page-break-after: always;\"/><img src=\"D:\\Project\\crunchymanga\\output\\Inside Mari\\ch003_p004.jpg\" title=\"Inside Mari Chapter 3 Page 65\" style=\"page-break-after: always;\"/><img src=\"D:\\Project\\crunchymanga\\output\\Inside Mari\\ch003_p005.jpg\" title=\"Inside Mari Chapter 3 Page 66\" style=\"page-break-after: always;\"/><img src=\"D:\\Project\\crunchymanga\\output\\Inside Mari\\ch003_p006.jpg\" title=\"Inside Mari Chapter 3 Page 67\" style=\"page-break-after: always;\"/><img src=\"D:\\Project\\crunchymanga\\output\\Inside Mari\\ch003_p007.jpg\" title=\"Inside Mari Chapter 3 Page 68\" style=\"page-break-after: always;\"/><img src=\"D:\\Project\\crunchymanga\\output\\Inside Mari\\ch003_p008.jpg\" title=\"Inside Mari Chapter 3 Page 69\" style=\"page-break-after: always;\"/><img src=\"D:\\Project\\crunchymanga\\output\\Inside Mari\\ch003_p009.jpg\" title=\"Inside Mari Chapter 3 Page 70\" style=\"page-break-after: always;\"/><img src=\"D:\\Project\\crunchymanga\\output\\Inside Mari\\ch003_p010.jpg\" title=\"Inside Mari Chapter 3 Page 71\" style=\"page-break-after: always;\"/><img src=\"D:\\Project\\crunchymanga\\output\\Inside Mari\\ch003_p011.jpg\" title=\"Inside Mari Chapter 3 Page 72\" style=\"page-break-after: always;\"/><img src=\"D:\\Project\\crunchymanga\\output\\Inside Mari\\ch003_p012.jpg\" title=\"Inside Mari Chapter 3 Page 73\" style=\"page-break-after: always;\"/><img src=\"D:\\Project\\crunchymanga\\output\\Inside Mari\\ch003_p013.jpg\" title=\"Inside Mari Chapter 3 Page 74\" style=\"page-break-after: always;\"/><img src=\"D:\\Project\\crunchymanga\\output\\Inside Mari\\ch003_p014.jpg\" title=\"Inside Mari Chapter 3 Page 75\" style=\"page-break-after: always;\"/><img src=\"D:\\Project\\crunchymanga\\output\\Inside Mari\\ch003_p015.jpg\" title=\"Inside Mari Chapter 3 Page 76\" style=\"page-break-after: always;\"/><img src=\"D:\\Project\\crunchymanga\\output\\Inside Mari\\ch003_p016.jpg\" title=\"Inside Mari Chapter 3 Page 77\" style=\"page-break-after: always;\"/><img src=\"D:\\Project\\crunchymanga\\output\\Inside Mari\\ch003_p017.jpg\" title=\"Inside Mari Chapter 3 Page 78\" style=\"page-break-after: always;\"/><img src=\"D:\\Project\\crunchymanga\\output\\Inside Mari\\ch003_p018.jpg\" title=\"Inside Mari Chapter 3 Page 79\" style=\"page-break-after: always;\"/><img src=\"D:\\Project\\crunchymanga\\output\\Inside Mari\\ch003_p019.jpg\" title=\"Inside Mari Chapter 3 Page 80\" style=\"page-break-after: always;\"/><img src=\"D:\\Project\\crunchymanga\\output\\Inside Mari\\ch003_p020.jpg\" title=\"Inside Mari Chapter 3 Page 81\" style=\"page-break-after: always;\"/><img src=\"D:\\Project\\crunchymanga\\output\\Inside Mari\\ch003_p021.jpg\" title=\"Inside Mari Chapter 3 Page 82\" style=\"page-break-after: always;\"/>"
    }
  ],
  "version": 3,
  "css": "@font-face {\r\n    font-family: \"Georgia\";\r\n    font-style: normal;\r\n    font-weight: normal;\r\n    src : url(\"./Georgia.ttf\");\r\n}\r\n\r\nhtml {\r\n    direction: rtl;\r\n}\r\n\r\nbody {\r\n    font-family: Georgia;\r\n    background-color: #fff;\r\n    color: #000;\r\n    margin: 0;\r\n    padding: 0;\r\n    line-height: 1.5em;\r\n}\r\n\r\na {\r\n    text-decoration: none;\r\n    color: #000;\r\n}\r\n\r\na:hover {\r\n    text-decoration: underline;\r\n}\r\n\r\nimg {\r\n    padding: 0;\r\n    height: 100%;\r\n    width: auto;\r\n    margin: auto auto auto auto;\r\n    page-break-before: always;\r\n}",
  "tocTitle": "Inside Mari",
  "appendChapterTitles": false
}